gbtgridder/__init__.py
gbtgridder/boxcar.py
gbtgridder/gbtgridder.py
gbtgridder/gbtgridder_args.py
gbtgridder/get_cube_info.py
gbtgridder/get_data.py
gbtgridder/grid_otf.py
gbtgridder/make_header.py
gbtgridder_20m-1.5.1.dist-info/METADATA
gbtgridder_20m-1.5.1.dist-info/WHEEL
gbtgridder_20m-1.5.1.dist-info/entry_points.txt
gbtgridder_20m-1.5.1.dist-info/RECORD
